[
    {
        "question": "电力、热力、燃气及水生产和供应业的营业成本同比增长了多少？",
        "answer": "19.4%。"
    },
    {
        "question": "采矿业的利润总额与去年同期相比增长了多少百分比？",
        "answer": "60.4%。"
    },
    {
        "question": "电力、热力、热力、燃气及水生产和供应业的营业收入金额及其同比增长分别是多少？",
        "answer": "营业收入金额为90884.1亿元，同比增长为18.4%。"
    },
    {
        "question": "表格中的总计列的营业收入金额（亿元）是多少？",
        "answer": "1117838.7亿元。"
    },
    {
        "question": "在表格中列出的所有行业中，哪个行业的营业收入金额最高？",
        "answer": "制造业，营业收入金额为971059.6亿元。"
    },
    {
        "question": "外商及港澳台商投资企业的营业收入同比增长了多少？",
        "answer": "3.6%。"
    },
    {
        "question": "股份制企业的营业收入同比增长跟营业成本的同比增长分别是多少？",
        "answer": "营业收入同比增长为8.5%，营业成本的同比增长为9.8%。"
    },
    {
        "question": "总计列的利润总额同比增长是多少？",
        "answer": "-3.0%。"
    },
    {
        "question": "国有控股企业的营业成本金额（亿元）是多少？",
        "answer": "246660.2亿元。"
    }
]