[
   {
      "question": "新能源汽车产量增长与整体汽车产量增长之间的百分比差异是多少？",
      "answer": "新能源汽车产量增长了150.5%，而整体汽车产量增长了11.1%。因此，新能源汽车与整体汽车增长之间的百分比差异是139.4%。",
      "id": "text2739",
      "tag": [
         "139.4"
      ]
   },
   {
      "question": "电力、热力生产和供应业增加值增长与制造业增加值增长之间的差值是多少？",
      "answer": "电力、热力、燃气及水生产和供应业增长了6.8%，而制造业增长了7.3%。两者之间的差值是0.5%。",
      "id": "text2740",
      "tag": [
         "0.5"
      ]
   },
   {
      "question": "煤炭开采和洗选业与石油和天然气开采业增加值增长的差值是多少？",
      "answer": "煤炭开采和洗选业增长了11.1%，而石油和天然气开采业增长了6.3%。因此，两者之间的增长差值是4.8%。",
      "id": "text2741",
      "tag": [
         "4.8"
      ]
   },
   {
      "question": "股份制企业增加值同比增长与私营企业增加值同比增长之间的差距是多少？",
      "answer": "股份制企业增长了8.4%，私营企业增长了8.7%。两者之间的增长差值是0.3%。",
      "id": "text2742",
      "tag": [
         "0.3"
      ]
   },
   {
      "question": "钢材产量的下降程度与水泥产量的下降程度相比，哪个更大？",
      "answer": "钢材产量下降了6.0%，水泥产量下降了17.8%。因此，水泥产量的下降程度更大，差异为11.8%。",
      "id": "text2743",
      "tag": [
         "水泥产量"
      ]
   },
   {
      "question": "电气机械和器材制造业增加值增速与计算机、通信和其他电子设备制造业增加值增速之间的差异是多少？",
      "answer": "电气机械和器材制造业增长了13.6%，而计算机、通信和其他电子设备制造业增长了12.7%。两者之间的差异是0.9%。",
      "id": "text2744",
      "tag": [
         "0.9"
      ]
   },
   {
      "question": "原油加工量的变化率与十种有色金属产量的变化率相比，差异是多少？",
      "answer": "原油加工量下降了1.1%，而十种有色金属产量下降了0.5%。两者的变化率差异是0.6%。",
      "id": "text2745",
      "tag": [
         "1.1",
         "0.5",
         "0.6"
      ]
   },
   {
      "question": "酒、饮料和精制茶制造业增加值增长率比纺织业高多少？",
      "answer": "酒、饮料和精制茶制造业增长了15.4%，纺织业增长了4.9%。两者之间的增长率差异是10.5%。",
      "id": "text2746",
      "tag": [
         "10.5"
      ]
   },
   {
      "question": "黑色金属冶炼和压延加工业相对于有色金属冶炼和压延加工业，下降多少百分点？",
      "answer": "黑色金属冶炼和压延加工业下降了2.9%，有色金属冶炼和压延加工业增长了4.4%。相对于增长，黑色金属下降了7.3百分点。",
      "id": "text2747",
      "tag": [
         "黑色金属冶炼",
         "有色金属冶炼",
         "下降",
         "2.9"
      ]
   },
   {
      "question": "电力、热力生产和供应业的增加值增长率与总体工业增加值增长率相比，低多少？",
      "answer": "电力、热力生产和供应业增长了6.8%，而总体规模以上工业增加值同比增长了7.5%。因此，电力、热力生产和供应业的增加值增长率比总体低0.7%。",
      "id": "text2748",
      "tag": [
         "0.7"
      ]
   }
]