[
   {
      "question": "2021年GDP最终核实数与初步核算数的差值是多少？",
      "answer": "2021年GDP最终核实数与初步核算数的差值为5567亿元。",
      "id": "text91",
      "tag": [
         "5567"
      ]
   },
   {
      "question": "2021年GDP最终核实数相比于初步核算数提高的百分点是多少？",
      "answer": "2021年GDP最终核实数相比于初步核算数提高了0.3个百分点。",
      "id": "text92",
      "tag": [
         "0.3"
      ]
   },
   {
      "question": "按照三次产业分类，第一产业与第二、三产业相比在GDP核算中的作用是如何区分的？",
      "answer": "在GDP核算中，第一产业主要指农林牧渔业，强调的是自然资源的开发利用；而第二产业主要包含制造业，强调的是加工制造和物质生产；第三产业即服务业，包含了除第一、第二产业以外的其他行业，强调的是服务提供。这三者在GDP核算中的作用区别在于它们各自在经济中的贡献和发展重点。",
      "id": "text94",
      "tag": [
         "农林牧渔业",
         "制造业",
         "服务业",
         "自然资源",
         "加工制造",
         "服务提供",
         "贡献",
         "发展重点"
      ]
   },
   {
      "question": "如果按现价与不变价计算2021年GDP的增长率，这两种计算方式下的增长率差别是什么？",
      "answer": "按现价计算的GDP增长率考虑了价格变动的影响，而按不变价格计算的GDP增长率则剔除了价格变动因素，更能反映经济量的实际变化。这两种计算方式下的增长率差别在于是否考虑了价格因素对GDP增长率的影响。",
      "id": "text95",
      "tag": [
         "价格变动",
         "剔除",
         "实际变化",
         "考虑"
      ]
   },
   {
      "question": "考虑到GDP数据采纳的国际核算原则及方法，中国GDP数据在国际上的可比性如何体现？",
      "answer": "中国GDP数据采纳联合国《国民账户体系（2008）》的核算原则和方法，这意味着中国的GDP核算标准与国际上通行的核算标准是一致的，因此，中国GDP数据在核算概念、核算方法和数据发布上与国际上的数据具有较高的可比性。",
      "id": "text97",
      "tag": [
         "联合国《国民账户体系（2008）》",
         "核算标准",
         "可比性"
      ]
   },
   {
      "question": "GDP数据在时间上的修订与更新对比较不同年份的GDP数据有何重要性？",
      "answer": "GDP数据在时间上的修订与更新保证了数据的准确性和可比性，尤其对于跨年度的经济分析来说尤为重要。这种修订和更新可以纠正先前数据的推算误差和信息的不完整，确保了不同年份间的GDP数据在核算标准和方法上保持一致，使得跨年度的经济状况比较成为可能。",
      "id": "text98",
      "tag": [
         "准确性",
         "可比性",
         "跨年度",
         "核算标准",
         "方法上保持一致"
      ]
   },
   {
      "question": "基于最终核实数据与初步核算数据的对比，GDP数据修订的频率和时间安排反映了什么样的核算特点？",
      "answer": "GDP数据从初步核算到最终核实的对比，以及修订的频率和时间安排，反映了GDP核算重视数据准确性和时效性的特点。通过适时修订，可以根据更全面、可靠的基础资料补充和修正先前的核算结果，从而确保GDP数据既能及时发布，又保留足够的灵活性以维护数据质量。",
      "id": "text99",
      "tag": [
         "数据准确性",
         "时效性",
         "全面",
         "可靠",
         "适时修订",
         "灵活性",
         "数据质量"
      ]
   },
   {
      "question": "在GDP年度核算中，使用的基础资料多样性对核算结果的准确性和可信性有何影响？",
      "answer": "在GDP年度核算中，使用的基础资料包括国家统计调查资料、部门年度财务统计资料、财政决算资料和行政管理部门的行政记录资料等。这些资料的多样性为GDP核算提供了全面、细致的经济活动信息，有助于提高GDP核算结果的准确性和可信性，因为这些资料能够从多个维度和角度反映经济的真实情况。",
      "id": "text100",
      "tag": [
         "国家统计调查资料",
         "部门年度财务统计资料",
         "财政决算资料",
         "行政记录资料",
         "全面",
         "细致",
         "提高准确性",
         "提高可信性",
         "多样性"
      ]
   }
]