[
   {
      "question": "2021年11月的所有指标数值中，哪个最低？",
      "answer": "'在手订单'最低，数值为45.7%。",
      "id": "table1838"
   },
   {
      "question": "哪个月的数据最为平衡，即每项指标数值最接近？",
      "answer": "需对每月的所有指标数值进行方差或标准差的计算，方差或标准差最小的月份即最为平衡。",
      "id": "table1839"
   },
   {
      "question": "'新出口订单'从2021年6月到2022年6月的平均值是多少？",
      "answer": "平均值约为47.2%（计算方法：求和后除以月份数）。",
      "id": "table1840"
   },
   {
      "question": "'在手订单'的最高值和最低值分别是多少，各出现在哪个月？",
      "answer": "最高值46.6%，出现在2021年6月；最低值为44.2%，出现在2022年6月。",
      "id": "table1841"
   },
   {
      "question": "哪一列的平均值最高？",
      "answer": "'主要原材料购进价格'列的平均值最高。",
      "id": "table1842"
   },
   {
      "question": "2022年1月'进口'数值相比2021年12月增长了多少百分点？",
      "answer": "减少了0.6个百分点（从48.2%减少到47.2%）。",
      "id": "table1843"
   },
   {
      "question": "从2021年6月到2022年6月，'生产经营活动预期'趋势如何？",
      "answer": "整体呈现先下降后上升的趋势。",
      "id": "table1844"
   },
   {
      "question": "'采购量'在表格中对应的数值单元格元组是什么？",
      "answer": "('C', 1, 3, '采购量')。",
      "id": "table1845"
   },
   {
      "question": "从表格中可以得知哪个季度的经济活动最为活跃？",
      "answer": "需要对比不同季度的所有相关指标的平均值，经济活动最活跃的季度将有最高的相关指标平均值。",
      "id": "table1846"
   },
   {
      "question": "在这段时间内，'出厂价格'是上涨趋势还是下跌趋势？",
      "answer": "根据数值的变化，总体是上涨趋势。",
      "id": "table1847"
   },
   {
      "question": "2021年6月的'出厂价格'的数值是多少？",
      "answer": "51.4%。",
      "id": "table1848"
   }
]