[
    {
        "question": "哪个城市在\"144m2以上\"住宅类型的\"定基\"数据最高？",
        "answer": "\"泸 州\"市在\"144m2以上\"住宅类型的\"定基\"数据最高，为121.2。"
    },
    {
        "question": "\"九 江\"在\"90m2及以下\"住宅类型的\"同比\"和\"定基\"数据分别是多少？",
        "answer": "\"九 江\"在\"90m2及以下\"住宅类型的\"同比\"是111.0，\"定基\"是141.6。"
    },
    {
        "question": "请问\"温 州\"在\"90-144m2\"住宅类型的\"定基\"是什么？",
        "answer": "\"温 州\"在\"90-144m2\"住宅类型的\"定基\"是119.7。"
    },
    {
        "question": "相对于其他城市，\"蚌 埠\"市在所有住宅类型的\"同比\"数据表现如何？",
        "answer": "\"蚌 埠\"市在各个住宅类型的\"同比\"数据与其他城市相比需手动评估，表格中没有直接比较。"
    },
    {
        "question": "\"金 华\"市在哪个住宅类型中\"环比\"数据最显著增长？",
        "answer": "\"金 华\"市在\"144m2以上\"住宅类型中\"环比\"数据最显著增长，为101.9。"
    },
    {
        "question": "表格中哪个城市在\"144m2及以上\"住宅类型的\"环比\"中呈现负增长？",
        "answer": "表格中没有城市在\"144m2及以上\"住宅类型的\"环比\"中呈现负增长。"
    },
    {
        "question": "请问\"秦 皇 岛\"在\"90m2及以下\"住宅类型的\"环比\"是多少？",
        "answer": "\"秦 皇 岛\"在\"90m2及以下\"住宅类型的\"环比\"是101.6。"
    },
    {
        "question": "\"牡 丹 江\"市在哪个住宅类型的\"环比\"数据下降了？",
        "answer": "\"牡 丹 江\"市的数据在表格中均为正增长，未显示下降。"
    },
    {
        "question": "\"泉 州\"市在所有住宅类型的\"定基\"中值是多少？",
        "answer": "\"泉 州\"市在所有住宅类型的\"定基\"中值需手动计算以得出。"
    },
    {
        "question": "在表格中，\"丹 东\"市\"90-144m2\"住宅的\"定基\"数值是多少？",
        "answer": "在表格中，\"丹 东\"市\"90-144m2\"住宅的\"定基\"数值是123.3。"
    },
    {
        "question": "\"安 庆\"在\"90-144m2\"住宅类型中\"定基\"数据表现如何？",
        "answer": "\"安 庆\"在\"90-144m2\"住宅类型中\"定基\"数据为126.9。"
    }
]