[
   {
      "question": "与制造业增长相比，电力、热力、燃气及水生产和供应业增加值同比增长了多少个百分点？",
      "answer": "电力、热力、燃气及水生产和供应业增加值同比增长比制造业高了10.5个百分点。",
      "id": "text885",
      "tag": [
         "10.5"
      ]
   },
   {
      "question": "与私营企业增长相比，国有控股企业增加值同比增长了多少个百分点？",
      "answer": "国有控股企业增加值同比增长比私营企业高了4.5个百分点。",
      "id": "text886",
      "tag": [
         "4.5"
      ]
   },
   {
      "question": "8月份水泥产量同比下降的百分比与钢材产量同比下降的百分比相比，哪个更高，相差多少个百分点？",
      "answer": "水泥产量同比下降的百分比比钢材产量下降的百分比高11.6个百分点。",
      "id": "text887",
      "tag": [
         "11.6"
      ]
   },
   {
      "question": "汽车产量同比增长的百分比与新能源汽车产量同比增长百分比相比，差值是多少？",
      "answer": "新能源汽车产量同比增长的百分比比汽车产量增长的百分比高78.0个百分点。",
      "id": "text888",
      "tag": [
         "78.0"
      ]
   },
   {
      "question": "8月份工业企业出口交货值同比增长的百分比与产品销售率同比变化的百分点相比，两者的绝对差值是多少？",
      "answer": "由于产品销售率是下降的，绝对差值计算为5.5%（出口增长） - (-0.4%)（销售率下降），即5.9个百分点。",
      "id": "text889",
      "tag": [
         "5.9"
      ]
   },
   {
      "question": "8月份电力、热力生产和供应业增加值同比增长与电力、热力、燃气及水生产和供应业增长值相比，差异是多少个百分点？",
      "answer": "由于均为同一个类别的不同描述，不存在差异，所以差异为0个百分点。",
      "id": "text890",
      "tag": [
         "0"
      ]
   },
   {
      "question": "在8月份中，新能源汽车产量同比增长百分比与有色金属产量同比增长百分比相比，前者高出多少个百分点？",
      "answer": "新能源汽车产量同比增长百分比比有色金属产量同比增长百分比高出110.3个百分点。",
      "id": "text891",
      "tag": [
         "110.3"
      ]
   },
   {
      "question": "采矿业增加值同比增长与制造业增加值同比增长之间的差值是多少？",
      "answer": "采矿业增加值同比增长与制造业增加值同比增长之间的差值是2.2个百分点。",
      "id": "text892",
      "tag": [
         "2.2"
      ]
   },
   {
      "question": "比较汽车制造业和计算机、通信和其他电子设备制造业8月份增加值同比增长百分比，哪个行业增长更快，差距是多少个百分点？",
      "answer": "汽车制造业增加值同比增长比计算机、通信和其他电子设备制造业快，差距是14.7个百分点。",
      "id": "text893",
      "tag": [
         "汽车制造业",
         "14.7"
      ]
   },
   {
      "question": "将8月份黑色金属冶炼和压延加工业的同比下降百分比与农副食品加工业的同比变化相比，两者的差值是多少个百分点？",
      "answer": "黑色金属冶炼和压延加工业与农副食品加工业的同比变化差值是0.9个百分点。",
      "id": "text894",
      "tag": [
         "0.9"
      ]
   }
]