[
  {
    "question": "原煤产量在2019年11月份比上一个月每日产量提高了多少万吨？",
    "answer": "2019年11月份原煤日均产量比上个月提高了66万吨。"
  },
  {
    "question": "煤炭进口在2019年11月份的增速比上一个月变化了多少个百分点？",
    "answer": "2019年11月份煤炭进口增速比上个月回落了2.9个百分点。"
  },
  {
    "question": "2019年11月份原油生产量的增速比上个月加快了多少个百分点？",
    "answer": "2019年11月份原油生产量的增速比上个月加快了0.9个百分点。"
  },
  {
    "question": "在2019年11月份，原油进口量同比增速与上月相比的变化是多少个百分点？",
    "answer": "在2019年11月份，原油进口量同比增速比上个月回落了10.4个百分点。"
  },
  {
    "question": "2019年11月份天然气生产的日均产量较上个月增加了多少亿立方米？",
    "answer": "2019年11月份天然气生产的日均产量较上个月增加了0.3亿立方米。"
  },
  {
    "question": "2019年11月份发电量日均比上个月增加了多少亿千瓦时？",
    "answer": "2019年11月份发电量日均比上个月增加了12.0亿千瓦时。"
  },
  {
    "question": "在2019年11月份，火电同比增速较上个月的变化情况是什么？",
    "answer": "2019年11月份火电同比增速比上个月回落了1.5个百分点。"
  },
  {
    "question": "2019年11月份水电同比降幅与上个月相比扩大了多少个百分点？",
    "answer": "2019年11月份水电同比降幅与上个月相比扩大了2.3个百分点。"
  },
  {
    "question": "核电在2019年11月份的同比增速与上个月比较，加快了多少个百分点？",
    "answer": "2019年11月份核电的同比增速比上个月加快了9.5个百分点。"
  },
  {
    "question": "2019年11月份太阳能发电同比增速与上个月比较，变化了多少个百分点？",
    "answer": "2019年11月份太阳能发电同比增速比上个月回落了0.3个百分点。"
  }
]