[
   {
      "question": "在建筑业商务活动指数图中，数据通过什么形式展现？",
      "answer": "单线折线图。",
      "tag": [
         "单线折线图"
      ],
      "id": "img1641"
   },
   {
      "question": "在建筑业商务活动指数图中，显示的时间跨度是多久？",
      "answer": "从2021年5月到2022年5月。",
      "tag": [
         "2021年5月",
         "2022年5月"
      ],
      "id": "img1642"
   },
   {
      "question": "在建筑业商务活动指数图中，2021年8月建筑业商务活动指数是多少?",
      "answer": "60.5。",
      "tag": [
         "60.5"
      ],
      "id": "img1643"
   },
   {
      "question": "在建筑业商务活动指数图中，2021年12月建筑业商务活动指数有增长还是下降？",
      "answer": "下降。",
      "tag": [
         "下降"
      ],
      "id": "img1644"
   },
   {
      "question": "在建筑业商务活动指数图中，2021年的建筑业商务活动指数均值是否在50以上？",
      "answer": "是的。",
      "tag": [
         "50以上"
      ],
      "id": "img1645"
   },
   {
      "question": "在建筑业商务活动指数图中，2021年11月的建筑业商务活动指数达到了多少？",
      "answer": "59.1。",
      "tag": [
         "59.1"
      ],
      "id": "img1646"
   }
]