[
  {
    "question": "工业生产者购进价格涨跌幅图中，2018年9月的同比涨跌幅是多少？",
    "answer": "4.2%"
  },
  {
    "question": "工业生产者购进价格涨跌幅图中，2019年1月环比涨跌幅是多少？",
    "answer": "-0.9%"
  },
  {
    "question": "工业生产者购进价格涨跌幅统计图中显示的最大同比涨跌幅是多少？",
    "answer": "4.8%"
  },
  {
    "question": "工业生产者购进价格涨跌幅统计图中显示的最低环比涨跌幅是多少？",
    "answer": "-0.9%"
  },
  {
    "question": "工业生产者购进价格涨跌幅图中，哪个月份显示了最大的同比涨跌幅？",
    "answer": "2018年8月。"
  },
  {
    "question": "工业生产者购进价格涨跌幅图中，2018年8月到2018年11月期间，同比涨跌幅是否一直在下降？",
    "answer": "是的。"
  }
]