[
  {
    "question": "秦皇岛港煤炭价格情况折线图的纵轴单位是什么？",
    "answer": "元/吨。"
  },
  {
    "question": "秦皇岛港煤炭价格情况图中，纵轴上表示的价格区间是多少？",
    "answer": "400元到650元。"
  },
  {
    "question": "秦皇岛港煤炭价格情况图中有哪几种煤炭的热值类型？",
    "answer": "5500大卡、5000大卡和4500大卡。"
  },
  {
    "question": "秦皇岛港煤炭价格情况折线图中的绿色虚线表示哪种热值的煤炭？",
    "answer": "5500大卡。"
  },
  {
    "question": "秦皇岛港煤炭价格情况折线图中的蓝色点线表示哪种热值的煤炭？",
    "answer": "5000大卡。"
  },
  {
    "question": "秦皇岛港煤炭价格情况折线图中的灰色实线表示哪种热值的煤炭？",
    "answer": "4500大卡。"
  },
  {
    "question": "秦皇岛港煤炭价格情况图中，在2019年中，5500大卡煤炭的价格是呈上升趋势还是下降趋势？",
    "answer": "先上升后下降。"
  },
  {
    "question": "根据秦皇岛港煤炭价格情况折线图，哪种热值的煤炭价格最高？",
    "answer": "5500大卡的煤炭价格最高。"
  }
]