[
  {
    "question": "秦皇岛港煤炭价格情况图表的单位是什么？",
    "answer": "元/吨。"
  },
  {
    "question": "秦皇岛港煤炭价格情况图表显示了哪三种煤炭的价格走势？",
    "answer": "5500大卡、5000大卡、4500大卡的煤炭。"
  },
  {
    "question": "在秦皇岛港煤炭价格情况图表中，煤炭价格是涨是跌还是波动？",
    "answer": "三种煤炭价格都呈现一定的波动。"
  },
  {
    "question": "秦皇岛港煤炭价格情况图中，纵轴代表的数值范围是多少？",
    "answer": "400元/吨至650元/吨。"
  },
  {
    "question": "秦皇岛港煤炭价格情况图中表示5500大卡煤炭价格的线条是什么样式？",
    "answer": "绿色的虚线。"
  },
  {
    "question": "秦皇岛港煤炭价格情况图中，表示5000大卡煤炭价格的线条是什么样式？",
    "answer": "蓝色的点线。"
  },
  {
    "question": "秦皇岛港煤炭价格情况图中，表示4500大卡煤炭价格的线条是什么样式？",
    "answer": "灰色的实线。"
  }
]