[
    {
        "question": "1-12月实物商品网上零售额的同比增长率是多少？",
        "answer": "19.5%"
    },
    {
        "question": "服装鞋帽、针纺织品类在1-12月期间的同比增长率是如何？",
        "answer": "2.9%"
    },
    {
        "question": "12月城镇消费品零售额绝对量是多少？",
        "answer": "32704亿元"
    },
    {
        "question": "化妆品类在12月的绝对量和同比增长率分别是多少？",
        "answer": "绝对量为280亿元，同比增长率为11.9%。"
    },
    {
        "question": "1-12月饮料类商品零售的同比增长率达到了多少？",
        "answer": "10.4%"
    },
    {
        "question": "1-12月汽车类商品零售的同比增长率达到了多少？",
        "answer": "-0.8%"
    },
    {
        "question": "1-12月金银珠宝类商品零售的同比增长率是多少？",
        "answer": "0.4%"
    },
    {
        "question": "1-12月商品零售中，粮油、食品类的绝对量是多少亿元？",
        "answer": "14525亿元"
    },
    {
        "question": "石油及制品类在12月期间的同比增长率是如何？",
        "answer": "4.0%"
    },
    {
        "question": "12月中，除汽车以外的消费品零售额同比增长率是多少？",
        "answer": "8.9%"
    },
    {
        "question": "通讯器材类在整个1-12月期间的绝对量与同比增长率分别是多少？",
        "answer": "绝对量为4839亿元，同比增长率为8.5%。"
    }
]