[
   {
      "question": "在煤炭进口月度走势图表中，2021年10月的煤炭进口量是多少万吨？",
      "answer": "2694万吨",
      "tag": [
         "2694"
      ],
      "id": "img336"
   },
   {
      "question": "在煤炭进口月度走势图表中，2021年10月煤炭进口量的增速是多少？",
      "answer": "98.7%",
      "tag": [
         "98.7"
      ],
      "id": "img337"
   },
   {
      "question": "在煤炭进口月度走势图表中，2021年11月的煤炭进口量是多少万吨？",
      "answer": "3505万吨",
      "tag": [
         "3505"
      ],
      "id": "img338"
   },
   {
      "question": "在煤炭进口月度走势图表中，2021年12月的煤炭进口量是多少万吨？",
      "answer": "3095万吨",
      "tag": [
         "3095"
      ],
      "id": "img339"
   },
   {
      "question": "在煤炭进口月度走势图表中，2022年1-2月的煤炭进口量是多少万吨？",
      "answer": "3539万吨",
      "tag": [
         "3539"
      ],
      "id": "img340"
   },
   {
      "question": "在煤炭进口月度走势图表中，2022年4月的煤炭进口量是多少万吨？",
      "answer": "2355万吨",
      "tag": [
         "2355"
      ],
      "id": "img341"
   },
   {
      "question": "在煤炭进口月度走势图表中，2022年5月的煤炭进口量是多少万吨？",
      "answer": "2055万吨",
      "tag": [
         "2055"
      ],
      "id": "img342"
   },
   {
      "question": "在煤炭进口月度走势图表中，煤炭进口的最大月度增速是什么时候，并且增速是多少？",
      "answer": "2021年11月，增速是200.5%",
      "tag": [
         "2021年11月",
         "200.5"
      ],
      "id": "img343"
   }
]