[
   {
      "question": "在所有城市中，有多少城市在“144m2以上”住宅类别的“定基”指标中超过了100？",
      "answer": "有4个城市的“定基”指标超过了100。",
      "id": "table1926",
      "tag": [
         "4个城市",
         "144m2以上",
         "定基",
         "超过了100"
      ]
   },
   {
      "question": "在“90-144m2”住宅类别中，所有城市的“同比”指标的均值是多少？",
      "answer": "大约为97.195。根据数据计算所有城市“同比”指标的平均值。",
      "id": "table1927",
      "tag": [
         "97.195"
      ]
   },
   {
      "question": "城市“三亚”的“144m2以上”住宅类别在“环比”方面的指数是多少？",
      "answer": "99.9",
      "id": "table1928",
      "tag": [
         "三亚",
         "144m2以上",
         "环比",
         "99.9"
      ]
   },
   {
      "question": "\"无锡\"在“90m2及以下”和“144m2以上”住房类别中的“同比”指数有何不同？",
      "answer": "\"无锡\"在“90m2及以下”类别的“同比”指数为101.9，而在“144m2以上”类别中为101.0，显示了少许下降。",
      "id": "table1929",
      "tag": [
         "101.9",
         "101.0",
         "下降"
      ]
   },
   {
      "question": "在所有城市中，有多少城市的“90m2及以下”住宅类别中的“环比”比“144m2以上”的“环比” 更高？",
      "answer": "需要对比每个城市在这两个类别中“环比”的数据，根据给定数据，大约有15个城市的“90m2及以下”类别的“环比”高于“144m2以上”的“环比”。",
      "id": "table1930",
      "tag": [
         "15"
      ]
   },
   {
      "question": "哪三个城市在“144m2以上”的“同比”中表现最好？",
      "answer": "“无锡”(101.0)、“徐州”(97.1) 和 “济宁”(97.6) 在“144m2以上”的同比中表现较好。",
      "id": "table1931",
      "tag": [
         "无锡",
         "徐州",
         "济宁"
      ]
   },
   {
      "question": "“秦皇岛”在所有住宅类别中“定基”指标的平均数是多少？",
      "answer": "平均定基指标为97.7。[(97.0+98.8+97.3) / 3]",
      "id": "table1932",
      "tag": [
         "平均",
         "定基指标",
         "97.7"
      ]
   },
   {
      "question": "哪个城市的“90m2及以下”住宅类别的“环比”最接近100？",
      "answer": "“秦皇岛”与“丹东”在“90m2及以下”住宅类别的环比均为100.0。",
      "id": "table1933",
      "tag": [
         "秦皇岛",
         "丹东",
         "90m2及以下",
         "环比"
      ]
   },
   {
      "question": "“泉州”在各个住宅大小类别的“定基”平均指数是多少？",
      "answer": "泉州的“定基”平均指数为（103.7+104.2+103.7）/ 3 = 103.87。",
      "id": "table1934",
      "tag": [
         "103.87"
      ]
   },
   {
      "question": "在“90-144m2”住宅类别中，“环比”表现最好的城市是哪个？",
      "answer": "无锡，其环比指数为100.7。",
      "id": "table1935",
      "tag": [
         "无锡",
         "100.7"
      ]
   },
   {
      "question": "“包头”在三种住宅类别的“环比”指数中表现如何？",
      "answer": "“包头”在三种住宅类别的“环比”指数分别为99.7（90m2及以下）、100.0（90-144m2）、99.7（144m2以上）。",
      "id": "table1936",
      "tag": [
         "99.7",
         "100.0"
      ]
   }
]